pycodestyle_magic.py
pycodestyle_magic-0.5.dist-info/LICENSE
pycodestyle_magic-0.5.dist-info/WHEEL
pycodestyle_magic-0.5.dist-info/METADATA
pycodestyle_magic-0.5.dist-info/RECORD
