Metadata-Version: 1.1
Name: pycodestyle_magic
Version: 0.5
Summary: magic function that checks a cell for pep8 compliance, using pycodestyle
Home-page: https://github.com/mattijn/pycodestyle_magic
Author: Mattijn van Hoek
Author-email: mattijn@gmail.com
